iqm/benchmarks/__init__.py
iqm/benchmarks/benchmark.py
iqm/benchmarks/benchmark_definition.py
iqm/benchmarks/circuit_containers.py
iqm/benchmarks/logging_config.py
iqm/benchmarks/readout_mitigation.py
iqm/benchmarks/utils.py
iqm/benchmarks/utils_plots.py
iqm/benchmarks/utils_shadows.py
iqm/benchmarks/coherence/__init__.py
iqm/benchmarks/coherence/coherence.py
iqm/benchmarks/compressive_gst/__init__.py
iqm/benchmarks/compressive_gst/compressive_gst.py
iqm/benchmarks/compressive_gst/gst_analysis.py
iqm/benchmarks/entanglement/__init__.py
iqm/benchmarks/entanglement/ghz.py
iqm/benchmarks/entanglement/graph_states.py
iqm/benchmarks/optimization/__init__.py
iqm/benchmarks/optimization/qscore.py
iqm/benchmarks/quantum_volume/__init__.py
iqm/benchmarks/quantum_volume/clops.py
iqm/benchmarks/quantum_volume/quantum_volume.py
iqm/benchmarks/randomized_benchmarking/__init__.py
iqm/benchmarks/randomized_benchmarking/clifford_1q.pkl
iqm/benchmarks/randomized_benchmarking/clifford_2q.pkl
iqm/benchmarks/randomized_benchmarking/multi_lmfit.py
iqm/benchmarks/randomized_benchmarking/randomized_benchmarking_common.py
iqm/benchmarks/randomized_benchmarking/clifford_rb/__init__.py
iqm/benchmarks/randomized_benchmarking/clifford_rb/clifford_rb.py
iqm/benchmarks/randomized_benchmarking/direct_rb/__init__.py
iqm/benchmarks/randomized_benchmarking/direct_rb/direct_rb.py
iqm/benchmarks/randomized_benchmarking/eplg/__init__.py
iqm/benchmarks/randomized_benchmarking/eplg/eplg.py
iqm/benchmarks/randomized_benchmarking/interleaved_rb/__init__.py
iqm/benchmarks/randomized_benchmarking/interleaved_rb/interleaved_rb.py
iqm/benchmarks/randomized_benchmarking/mirror_rb/__init__.py
iqm/benchmarks/randomized_benchmarking/mirror_rb/mirror_rb.py
iqm_benchmarks-2.55.dist-info/licenses/LICENSE
mGST/LICENSE
mGST/README.md
mGST/additional_fns.py
mGST/algorithm.py
mGST/compatibility.py
mGST/low_level_jit.py
mGST/optimization.py
mGST/qiskit_interface.py
mGST/reporting/figure_gen.py
mGST/reporting/reporting.py
iqm_benchmarks-2.55.dist-info/METADATA
iqm_benchmarks-2.55.dist-info/WHEEL
iqm_benchmarks-2.55.dist-info/top_level.txt
iqm_benchmarks-2.55.dist-info/RECORD
