Metadata-Version: 2.4
Name: iqm-benchmarks
Version: 2.55
Summary: A package for implementation of Quantum Characterization, Verification and Validation (QCVV) techniques on IQM's hardware at gate level abstraction
Author-email: IQM Finland Oy <developers@meetiqm.com>, Adrian Auer <adrian.auer@meetiqm.com>, Raphael Brieger <raphael.brieger@meetiqm.com>, Alessio Calzona <alessio.calzona@meetiqm.com>, Pedro Figueroa Romero <pedro.romero@meetiqm.com>, Amin Hosseinkhani <amin.hosseinkhani@meetiqm.com>, Miikka Koistinen <miikka@meetiqm.com>, Nadia Milazzo <nadia.milazzo@meetiqm.com>, Vicente Pina Canelles <vicente.pina@meetiqm.com>, Aniket Rath <aniket.rath@meetiqm.com>, Jami Rönkkö <jami@meetiqm.com>, Stefan S
Project-URL: Homepage, https://github.com/iqm-finland/iqm-benchmarks
Classifier: Development Status :: 4 - Beta
Classifier: Programming Language :: Python :: 3 :: Only
Classifier: Topic :: Scientific/Engineering :: Physics
Classifier: Intended Audience :: Science/Research
Requires-Python: <3.13,>=3.11
License-File: LICENSE
Requires-Dist: lmfit>=1.2
Requires-Dist: matplotlib<4,>=3.6.3
Requires-Dist: more-itertools<11.0.0,>=10.1.0
Requires-Dist: mthree<2.7,>=2.6
Requires-Dist: networkx<4.0,>=3.3
Requires-Dist: rustworkx>=0.16.0
Requires-Dist: numpy<2.0,>=1.25.2
Requires-Dist: qiskit<=1.4.2,>=1.2.4
Requires-Dist: iqm-client[qiskit]<34.0,>=32.1.1
Requires-Dist: qiskit-ibm-runtime<0.44.0
Requires-Dist: iqm-station-control-client<13.0,>=11.3.1
Requires-Dist: requests<3.0,>=2.32.3
Requires-Dist: scikit-optimize<0.11.0,>=0.10.2
Requires-Dist: tabulate<1.0.0,>=0.9.0
Requires-Dist: uncertainties<3.3.0,>=3.2.2
Requires-Dist: pycurl<8.0,>=7.45.3
Requires-Dist: xarray<2025.0.0,>=2024.6.0
Requires-Dist: types-requests
Requires-Dist: myst-nb==1.3.0
Requires-Dist: pyyaml!=5.4.0,!=5.4.1,!=6.0.0
Provides-Extra: cicd
Requires-Dist: build==1.0.3; extra == "cicd"
Requires-Dist: pip-licenses==5.0.0; extra == "cicd"
Provides-Extra: examples
Requires-Dist: notebook==7.2.1; extra == "examples"
Provides-Extra: mgst
Requires-Dist: numba>=0.61.0; extra == "mgst"
Requires-Dist: pygsti[diamond_norm]==0.9.12.3; extra == "mgst"
Requires-Dist: tqdm==4.66.5; extra == "mgst"
Provides-Extra: test
Requires-Dist: black==24.4.2; extra == "test"
Requires-Dist: isort==5.13.2; extra == "test"
Requires-Dist: mypy==1.10.1; extra == "test"
Requires-Dist: pylint==3.2.5; extra == "test"
Requires-Dist: pytest==7.4.4; extra == "test"
Requires-Dist: pytest-cov==4.1.0; extra == "test"
Requires-Dist: pytest-isort==3.1.0; extra == "test"
Requires-Dist: pytest-mypy==0.10.3; extra == "test"
Requires-Dist: pytest-pylint==0.21.0; extra == "test"
Provides-Extra: docs
Requires-Dist: sphinx==7.2.6; extra == "docs"
Requires-Dist: sphinx-book-theme==1.1.2; extra == "docs"
Requires-Dist: myst-parser<5,>=4.0.0; extra == "docs"
Dynamic: license-file
